py_sma_modbus/__init__.py
py_sma_modbus/format_unit.py
py_sma_modbus/modbus.py
py_sma_modbus/registers.py
py_sma_modbus-0.2.0.dist-info/METADATA
py_sma_modbus-0.2.0.dist-info/WHEEL
py_sma_modbus-0.2.0.dist-info/RECORD
