Metadata-Version: 2.1
Name: py_sma_modbus
Version: 0.2.0
Summary: This package can be used to read values from a SMA inverter through Modbus TCP.
Author: Tim Groß
Author-email: info@tim-gross.de
Requires-Python: >=3.12,<4.0
Classifier: Programming Language :: Python :: 3
Classifier: Programming Language :: Python :: 3.12
Requires-Dist: pymodbus (==2.3.0)
